ndexncipidloader/__init__.py
ndexncipidloader/exceptions.py
ndexncipidloader/gene_symbol_mapping.json
ndexncipidloader/loadplan.json
ndexncipidloader/ndexloadncipid.py
ndexncipidloader/network.py
ndexncipidloader/networkattributes.tsv
ndexncipidloader/style.cx
ndexncipidloader-5.0.1.data/scripts/ndexloadncipid.py
ndexncipidloader-5.0.1.dist-info/AUTHORS.rst
ndexncipidloader-5.0.1.dist-info/LICENSE
ndexncipidloader-5.0.1.dist-info/METADATA
ndexncipidloader-5.0.1.dist-info/WHEEL
ndexncipidloader-5.0.1.dist-info/top_level.txt
ndexncipidloader-5.0.1.dist-info/RECORD
