Metadata-Version: 2.1
Name: ndexncipidloader
Version: 5.0.1
Summary: Loads NCI-PID data into NDEx
Home-page: https://github.com/ndexcontent/ndexncipidloader
Author: Chris Churas
Author-email: contact@ndexbio.org
License: BSD license
Keywords: ndexncipidloader
Platform: UNKNOWN
Classifier: Development Status :: 2 - Pre-Alpha
Classifier: Intended Audience :: Developers
Classifier: License :: OSI Approved :: BSD License
Classifier: Natural Language :: English
Classifier: Programming Language :: Python :: 3.6
Classifier: Programming Language :: Python :: 3.7
Requires-Dist: ndex2 (<4.0.0,>=3.4.0)
Requires-Dist: ndexutil (<1.0.0,>=0.13.0)
Requires-Dist: biothings-client
Requires-Dist: ftpretty
Requires-Dist: requests
Requires-Dist: pandas
Requires-Dist: py4cytoscape
